drawio/__init__.py
drawio/drawio.py
drawio-0.0.10.dist-info/LICENSE
drawio-0.0.10.dist-info/METADATA
drawio-0.0.10.dist-info/WHEEL
drawio-0.0.10.dist-info/top_level.txt
drawio-0.0.10.dist-info/RECORD
